nixietune/__init__.py
nixietune/arguments.py
nixietune/log.py
nixietune/biencoder/__init__.py
nixietune/biencoder/__main__.py
nixietune/biencoder/arguments.py
nixietune/biencoder/layout.py
nixietune/biencoder/main.py
nixietune/biencoder/trainer.py
nixietune/biencoder/loss/infonce.py
nixietune/biencoder/loss/mixed.py
nixietune/crossencoder/__main__.py
nixietune/crossencoder/arguments.py
nixietune/crossencoder/dataset.py
nixietune/crossencoder/trainer.py
nixietune/format/json.py
nixietune/format/jsontokenized.py
nixietune/metrics/callback.py
nixietune/metrics/metrics.py
nixietune/negative/generate/__main__.py
nixietune/negative/generate/gen.py
nixietune/querygen/generate/__main__.py
nixietune/querygen/generate/generate.py
nixietune/querygen/merge/__main__.py
nixietune/querygen/train/__main__.py
nixietune/querygen/train/arguments.py
nixietune/querygen/train/main.py
nixietune/querygen/train/tokenizer.py
nixietune/querygen/train/trainer.py
nixietune/ranker/__main__.py
nixietune/ranker/arguments.py
nixietune/ranker/trainer.py
nixietune/util/eval_callback.py
nixietune-0.0.7.dist-info/METADATA
nixietune-0.0.7.dist-info/WHEEL
nixietune-0.0.7.dist-info/licenses/LICENSE
nixietune-0.0.7.dist-info/RECORD
