Metadata-Version: 2.3
Name: nixietune
Version: 0.0.7
Summary: A semantic search embedding model fine-tuning tool
Project-URL: Homepage, https://github.com/nixiesearch/nixietune
Project-URL: Issues, https://github.com/nixiesearch/nixietune/issues
Author-email: Grebennikov Roman <grv@dfdx.me>
License-File: LICENSE
Classifier: Development Status :: 3 - Alpha
Classifier: Environment :: GPU
Classifier: License :: OSI Approved :: MIT License
Classifier: Operating System :: OS Independent
Classifier: Programming Language :: Python :: 3
Classifier: Topic :: Scientific/Engineering :: Artificial Intelligence
Requires-Python: >=3.10
Requires-Dist: accelerate
Requires-Dist: bitsandbytes
Requires-Dist: datasets
Requires-Dist: evaluate
Requires-Dist: hnswlib
Requires-Dist: info-nce-pytorch
Requires-Dist: peft
Requires-Dist: sentence-transformers
Requires-Dist: sentencepiece
Requires-Dist: torch
Requires-Dist: torchmetrics
Requires-Dist: transformers
Requires-Dist: trl
Requires-Dist: wandb
Requires-Dist: wheel
Requires-Dist: zstandard
Provides-Extra: test
Requires-Dist: pytest; extra == 'test'
Requires-Dist: pytest-skip-slow; extra == 'test'
Requires-Dist: ruff; extra == 'test'
